.gitignore
.requires
.test-requires
LICENSE
MANIFEST.in
README.rst
aversion.py
setup.py
test_aversion.py
tox.ini
aversion.egg-info/PKG-INFO
aversion.egg-info/SOURCES.txt
aversion.egg-info/dependency_links.txt
aversion.egg-info/entry_points.txt
aversion.egg-info/requires.txt
aversion.egg-info/top_level.txt