Metadata-Version: 1.0
Name: aversion
Version: 0.1.0
Summary: AVersion WSGI Version Selection Application
Home-page: https://github.com/klmitch/aversion
Author: Kevin L. Mitchell
Author-email: kevin.mitchell@rackspace.com
License: Apache License (2.0)
Platform: UNKNOWN
Classifier: Development Status :: 4 - Beta
Classifier: License :: OSI Approved :: Apache Software License
Classifier: Environment :: Web Environment
Classifier: Intended Audience :: System Administrators
Classifier: Operating System :: OS Independent
Classifier: Framework :: Paste
Classifier: Programming Language :: Python
